{
  "id": 10333,
  "name": "zigzagoon-galar",
  "form_name": "galar",
  "is_default": true,
  "is_battle_only": false,
  "is_mega": false,
  "order": 390,
  "form_order": 2,
  "pokemon": {
    "name": "zigzagoon-galar",
    "url": "https://pokeapi.co/api/v2/pokemon/10174/"
  },
  "sprites": {
    "front_default": "https://raw.githubusercontent.com/PokeAPI/sprites/master/sprites/pokemon/10174.png",
    "front_shiny": "https://raw.githubusercontent.com/PokeAPI/sprites/master/sprites/pokemon/shiny/10174.png",
    "back_default": "https://raw.githubusercontent.com/PokeAPI/sprites/master/sprites/pokemon/back/10174.png",
    "back_shiny": "https://raw.githubusercontent.com/PokeAPI/sprites/master/sprites/pokemon/back/shiny/10174.png"
  },
  "types": [
    {
      "slot": 1,
      "type": {
        "name": "dark",
        "url": "https://pokeapi.co/api/v2/type/17/"
      }
    },
    {
      "slot": 2,
      "type": {
        "name": "normal",
        "url": "https://pokeapi.co/api/v2/type/1/"
      }
    }
  ]
}