{
  "id": 10385,
  "name": "flapple-gmax",
  "form_name": "gmax",
  "is_default": true,
  "is_battle_only": true,
  "is_mega": false,
  "order": 1270,
  "form_order": 1,
  "pokemon": {
    "name": "flapple-gmax",
    "url": "https://pokeapi.co/api/v2/pokemon/10216/"
  },
  "sprites": {
    "front_default": "https://raw.githubusercontent.com/PokeAPI/sprites/master/sprites/pokemon/10216.png",
    "front_shiny": "https://raw.githubusercontent.com/PokeAPI/sprites/master/sprites/pokemon/shiny/10216.png",
    "back_default": null,
    "back_shiny": null
  },
  "types": [
    {
      "slot": 1,
      "type": {
        "name": "grass",
        "url": "https://pokeapi.co/api/v2/type/12/"
      }
    },
    {
      "slot": 2,
      "type": {
        "name": "dragon",
        "url": "https://pokeapi.co/api/v2/type/16/"
      }
    }
  ]
}